pretty_upper/__init__.py
pretty_upper/cli.py
pretty_upper/pretty_upper.py
pretty_upper-0.3.1.dist-info/DESCRIPTION.rst
pretty_upper-0.3.1.dist-info/METADATA
pretty_upper-0.3.1.dist-info/RECORD
pretty_upper-0.3.1.dist-info/WHEEL
pretty_upper-0.3.1.dist-info/entry_points.txt
pretty_upper-0.3.1.dist-info/metadata.json
pretty_upper-0.3.1.dist-info/top_level.txt
