Metadata-Version: 2.0
Name: pretty-upper
Version: 0.3.1
Summary: Removes accents from vowels when a Greek word/sentence is all capitals
Home-page: https://github.com/manikos/pretty_upper
Author: Nick Mavrakis
Author-email: mavrakis.n@gmail.com
License: MIT license
Keywords: pretty_upper
Platform: UNKNOWN
Classifier: Development Status :: 2 - Pre-Alpha
Classifier: Intended Audience :: Developers
Classifier: License :: OSI Approved :: MIT License
Classifier: Natural Language :: English
Classifier: Programming Language :: Python :: 2
Classifier: Programming Language :: Python :: 2.7
Classifier: Programming Language :: Python :: 3
Classifier: Programming Language :: Python :: 3.4
Classifier: Programming Language :: Python :: 3.5
Classifier: Programming Language :: Python :: 3.6
Requires-Dist: Click (>=6.0)
